odoo9_addon_web_duplicate_visibility-9.0.1.0.1-py2.7-nspkg.pth
odoo9_addon_web_duplicate_visibility-9.0.1.0.1.dist-info/top_level.txt
odoo9_addon_web_duplicate_visibility-9.0.1.0.1.dist-info/WHEEL
odoo9_addon_web_duplicate_visibility-9.0.1.0.1.dist-info/RECORD
odoo9_addon_web_duplicate_visibility-9.0.1.0.1.dist-info/metadata.json
odoo9_addon_web_duplicate_visibility-9.0.1.0.1.dist-info/DESCRIPTION.rst
odoo9_addon_web_duplicate_visibility-9.0.1.0.1.dist-info/METADATA
odoo9_addon_web_duplicate_visibility-9.0.1.0.1.dist-info/namespace_packages.txt
odoo_addons/web_duplicate_visibility/__openerp__.py
odoo_addons/web_duplicate_visibility/__init__.py
odoo_addons/web_duplicate_visibility/README.rst
odoo_addons/web_duplicate_visibility/views/assets.xml
odoo_addons/web_duplicate_visibility/tests/test_js.py
odoo_addons/web_duplicate_visibility/tests/__init__.py
odoo_addons/web_duplicate_visibility/demo/res_users_view.xml
odoo_addons/web_duplicate_visibility/static/test/duplicate_visibility.js
odoo_addons/web_duplicate_visibility/static/src/js/duplicate_visibility.js
